pycbr/__init__.py
pycbr/aggregate.py
pycbr/casebase.py
pycbr/models.py
pycbr/nlp.py
pycbr/recovery.py
pycbr/server.py
pycbr-0.2.3.dist-info/LICENSE.txt
pycbr-0.2.3.dist-info/METADATA
pycbr-0.2.3.dist-info/WHEEL
pycbr-0.2.3.dist-info/top_level.txt
pycbr-0.2.3.dist-info/RECORD
