Metadata-Version: 2.1
Name: pycbr
Version: 0.2.3
Summary: Package to implement Case-Based Reasoning systems
Home-page: https://github.com/dih5/pycbr
Author: Dih5
Author-email: dihedralfive@gmail.com
Classifier: Development Status :: 3 - Alpha
Classifier: Intended Audience :: Science/Research
Classifier: License :: OSI Approved :: GNU Lesser General Public License v3 (LGPLv3)
Classifier: Natural Language :: English
Classifier: Programming Language :: Python :: 3
Classifier: Programming Language :: Python :: 3.5
Classifier: Programming Language :: Python :: 3.6
Classifier: Programming Language :: Python :: 3.7
Classifier: Programming Language :: Python :: 3.8
Classifier: Programming Language :: Python :: 3.9
Classifier: Programming Language :: Python :: 3.10
Classifier: Programming Language :: Python :: 3.11
License-File: LICENSE.txt
Requires-Dist: numpy
Requires-Dist: pandas
Requires-Dist: scikit-learn
Requires-Dist: flask
Requires-Dist: flask-restx
Requires-Dist: flask-cors
Requires-Dist: coloredlogs
Requires-Dist: pyyaml
Requires-Dist: werkzeug <1.0
Provides-Extra: docs
Requires-Dist: nbsphinx ; extra == 'docs'
Requires-Dist: sphinx-rtd-theme ; extra == 'docs'
Requires-Dist: IPython ; extra == 'docs'
Provides-Extra: test
Requires-Dist: pytest ; extra == 'test'
Provides-Extra: text
Requires-Dist: nltk ; extra == 'text'
